{
    "name": "Default Light",
    "version": "1.0",
    "variables": {
        "boldFont": "not implemented yet"
    },
    "editor": {
        "backgroundColor": "#FFFFFF",
        "tintColor": "#000000",
        "cursorColor": "#000000"
    },
    "styles": {
        "h1": {
            "font": "LibreFranklin-ExtraBold",
            "color": "#000000",
            "size": 36
        },
        "h2": {
            "font": "LibreFranklin-ExtraBold",
            "color": "#000000",
            "size": 28
        },
        "h3": {
            "font": "LibreFranklin-ExtraBold",
            "color": "#000000",
            "size": 20
        },
        "h4": {
            "font": "LibreFranklin-Bold",
            "color": "#000000",
            "size": 18
        },
        "h5": {
            "font": "LibreFranklin-SemiBold",
            "color": "#000000",
            "size": 16
        },
        "h6": {
            "font": "LibreFranklin-SemiBold",
            "color": "#000000",
            "size": 15,
        },
        "body": {
            "font": "LibreFranklin-Regular",
            "size": 15,
            "color": "#000000"
        },
        "bold": {
            "font": "LibreFranklin-Bold",
            "color": "#b2675e"
        },
        "italic": {
            "font": "LibreFranklin-Italic",
            "color": "#F2B635"
        },
        "link": {
            "font": "LibreFranklin-Regular",
            "color": "#119dd0"
        },
        "image": {
            "color": "#a66bff"
        },
        "inlineCode": {
            "font": "CourierNew",
            "color": "#e07a5f",
            "size": 15
        },
        "codeBlock": {
            "font": "CourierNew",
            "color": "#e07a5f",
            "size": 15
        },
        "blockQuote": {
            "font": "HelveticaNeue-LightItalic",
            "color": "#B9B9C0",
            "size": 15
        },
        "list": {
            "font": "LibreFranklin-Regular",
            "color": "#09c8bd",
            "size": 15,
        },
        "quoteStripe": {
            "color": "#09c8a9"
        },
        "codeBlockBackground": {
            "color": "#f2f2f3"
        },
        "thematicBreak": {
            "color": "f2f2f3"
        }
    }
}
